{
    "iteration": 70,
    "strats_frame": {
        "ACB": [
            0,
            []
        ],
        "ACE": [
            1260,
            {
                "E": 1260
            }
        ],
        "ACD": [
            728,
            {
                "D": 728
            }
        ],
        "ACF": [
            876,
            {
                "F": 876
            }
        ],
        "ABD": [
            1669,
            {
                "D": 772,
                "B": 317,
                "FD": 580
            }
        ]
    }
}